scrappers.py
torrent_scrappers-0.0.1.dist-info/licenses/LICENSE
torrent_scrappers-0.0.1.dist-info/WHEEL
torrent_scrappers-0.0.1.dist-info/METADATA
torrent_scrappers-0.0.1.dist-info/RECORD
