Metadata-Version: 2.4
Name: torrent-scrappers
Version: 0.0.1
Summary: Simple collection of scrappers of popular torrent sites.
Author-email: Łukasz Flisak <lu.dev00@gmail.com>
Requires-Python: >=3.10
License-Expression: GPL-3.0-or-later
Classifier: Programming Language :: Python :: 3.10
Classifier: Development Status :: 3 - Alpha
Classifier: Intended Audience :: Developers
Classifier: Operating System :: OS Independent
License-File: LICENSE
Requires-Dist: beautifulsoup4>=4.13.3
Requires-Dist: requests>=2.32.3
Project-URL: Homepage, https://github.com/flisakl/torrent-scrappers
Project-URL: Issues, https://github.com/flisakl/torrent-scrappers/issues
